LICENSE.txt
MANIFEST.in
setup.cfg
setup.py
viralata/__init__.py
viralata/app.py
viralata/auths.py
viralata/cutils.py
viralata/extensions.py
viralata/models.py
viralata/utils.py
viralata/views.py
viralata.egg-info/PKG-INFO
viralata.egg-info/SOURCES.txt
viralata.egg-info/dependency_links.txt
viralata.egg-info/requires.txt
viralata.egg-info/top_level.txt