Metadata-Version: 1.1
Name: viralata
Version: 0.1
Summary: Microservice for Authentication: Restlike & Social.
Home-page: https://gitlab.com/ok-br/viralata
Author: Andrés M. R. Martano
Author-email: andres@inventati.org
License: UNKNOWN
Keywords: authentication,microservice
Platform: UNKNOWN
Classifier: Development Status :: 3 - Alpha
Classifier: Environment :: Web Environment
Classifier: Intended Audience :: Developers
Classifier: License :: OSI Approved :: GNU Affero General Public License v3 or later (AGPLv3+)
Classifier: Operating System :: OS Independent
Classifier: Programming Language :: Python
Classifier: Programming Language :: Python :: 2
Classifier: Programming Language :: Python :: 3
Classifier: Environment :: Web Environment
Classifier: Topic :: Internet :: WWW/HTTP
Classifier: Topic :: Internet :: WWW/HTTP :: Session
